<annotation verified="no">
  <folder>RBC</folder>
  <filename>BloodImage_00397</filename>
  <path>/Users/cosmic/WBC_CLASSIFICATION_ANNO/RBC/BloodImage_00397.jpg</path>
  <source>
    <database>Unknown</database>
  </source>
  <size>
    <width>640</width>
    <height>480</height>
    <depth>3</depth>
  </size>
  <segmented>0</segmented>
  <object>
    <name>RBC</name>
    <pose>Unspecified</pose>
    <truncated>0</truncated>
    <difficult>0</difficult>
    <bndbox>
      <xmin>68</xmin>
      <ymin>154</ymin>
      <xmax>165</xmax>
      <ymax>249</ymax>
    </bndbox>
  </object>
  <object>
    <name>RBC</name>
    <pose>Unspecified</pose>
    <truncated>1</truncated>
    <difficult>0</difficult>
    <bndbox>
      <xmin>1</xmin>
      <ymin>145</ymin>
      <xmax>66</xmax>
      <ymax>260</ymax>
    </bndbox>
  </object>
  <object>
    <name>RBC</name>
    <pose>Unspecified</pose>
    <truncated>0</truncated>
    <difficult>0</difficult>
    <bndbox>
      <xmin>207</xmin>
      <ymin>160</ymin>
      <xmax>334</xmax>
      <ymax>270</ymax>
    </bndbox>
  </object>
  <object>
    <name>RBC</name>
    <pose>Unspecified</pose>
    <truncated>0</truncated>
    <difficult>0</difficult>
    <bndbox>
      <xmin>435</xmin>
      <ymin>347</ymin>
      <xmax>540</xmax>
      <ymax>437</ymax>
    </bndbox>
  </object>
  <object>
    <name>RBC</name>
    <pose>Unspecified</pose>
    <truncated>0</truncated>
    <difficult>0</difficult>
    <bndbox>
      <xmin>535</xmin>
      <ymin>356</ymin>
      <xmax>639</xmax>
      <ymax>464</ymax>
    </bndbox>
  </object>
  <object>
    <name>RBC</name>
    <pose>Unspecified</pose>
    <truncated>0</truncated>
    <difficult>0</difficult>
    <bndbox>
      <xmin>446</xmin>
      <ymin>221</ymin>
      <xmax>550</xmax>
      <ymax>329</ymax>
    </bndbox>
  </object>
  <object>
    <name>RBC</name>
    <pose>Unspecified</pose>
    <truncated>1</truncated>
    <difficult>0</difficult>
    <bndbox>
      <xmin>509</xmin>
      <ymin>94</ymin>
      <xmax>640</xmax>
      <ymax>207</ymax>
    </bndbox>
  </object>
  <object>
    <name>RBC</name>
    <pose>Unspecified</pose>
    <truncated>0</truncated>
    <difficult>0</difficult>
    <bndbox>
      <xmin>456</xmin>
      <ymin>3</ymin>
      <xmax>560</xmax>
      <ymax>111</ymax>
    </bndbox>
  </object>
  <object>
    <name>RBC</name>
    <pose>Unspecified</pose>
    <truncated>0</truncated>
    <difficult>0</difficult>
    <bndbox>
      <xmin>354</xmin>
      <ymin>144</ymin>
      <xmax>458</xmax>
      <ymax>252</ymax>
    </bndbox>
  </object>
  <object>
    <name>RBC</name>
    <pose>Unspecified</pose>
    <truncated>0</truncated>
    <difficult>0</difficult>
    <bndbox>
      <xmin>169</xmin>
      <ymin>317</ymin>
      <xmax>277</xmax>
      <ymax>455</ymax>
    </bndbox>
  </object>
  <object>
    <name>RBC</name>
    <pose>Unspecified</pose>
    <truncated>0</truncated>
    <difficult>0</difficult>
    <bndbox>
      <xmin>64</xmin>
      <ymin>302</ymin>
      <xmax>166</xmax>
      <ymax>406</ymax>
    </bndbox>
  </object>
  <object>
    <name>RBC</name>
    <pose>Unspecified</pose>
    <truncated>0</truncated>
    <difficult>0</difficult>
    <bndbox>
      <xmin>74</xmin>
      <ymin>200</ymin>
      <xmax>176</xmax>
      <ymax>304</ymax>
    </bndbox>
  </object>
  <object>
    <name>RBC</name>
    <pose>Unspecified</pose>
    <truncated>0</truncated>
    <difficult>0</difficult>
    <bndbox>
      <xmin>141</xmin>
      <ymin>18</ymin>
      <xmax>217</xmax>
      <ymax>109</ymax>
    </bndbox>
  </object>
  <object>
    <name>RBC</name>
    <pose>Unspecified</pose>
    <truncated>0</truncated>
    <difficult>0</difficult>
    <bndbox>
      <xmin>316</xmin>
      <ymin>47</ymin>
      <xmax>409</xmax>
      <ymax>141</ymax>
    </bndbox>
  </object>
  <object>
    <name>RBC</name>
    <pose>Unspecified</pose>
    <truncated>1</truncated>
    <difficult>0</difficult>
    <bndbox>
      <xmin>356</xmin>
      <ymin>1</ymin>
      <xmax>465</xmax>
      <ymax>56</ymax>
    </bndbox>
  </object>
  <object>
    <name>RBC</name>
    <pose>Unspecified</pose>
    <truncated>0</truncated>
    <difficult>0</difficult>
    <bndbox>
      <xmin>35</xmin>
      <ymin>65</ymin>
      <xmax>128</xmax>
      <ymax>159</ymax>
    </bndbox>
  </object>
  <object>
    <name>RBC</name>
    <pose>Unspecified</pose>
    <truncated>0</truncated>
    <difficult>0</difficult>
    <bndbox>
      <xmin>66</xmin>
      <ymin>371</ymin>
      <xmax>181</xmax>
      <ymax>463</ymax>
    </bndbox>
  </object>
</annotation>
